Workbook

Sheet Summary
A1: Lekha - finance & order-to-cash summary
A2: SYNTHETIC, SAP-STYLE (simplified) data generated by Lekha. Not real SAP data; no SAP connection.
A3: As-of date | B3: 46022
A5: Open receivables | B5: =Aging!C7
A6: Overdue 90+ days | B6: =Aging!C6
A7: Overdue 90+ share of open AR | B7: =IFERROR(Aging!C6/Aging!C7,0)
A8: DSO - latest month (days) | B8: =DSO!D37
A9: Total budget variance, last 12 periods | B9: =SUM(Variance!E2:E241)
A10: Revenue, last 12 periods | B10: =SUM(PnL!B26:B37)
A11: EBIT, last 12 periods | B11: =SUM(PnL!F26:F37)

Sheet AR_Open
A1: Invoice | B1: Customer | C1: Invoice date | D1: Due date | E1: Amount | F1: Days overdue | G1: Bucket
A2: 0009000049 | B2: 0000100293 | C2: 44937 | D2: 44967 | E2: 245.56 | F2: =Summary!$B$3-D2 | G2: =IF(D2>Summary!$B$3,"Current",IF(F2<=30,"0-30",IF(F2<=60,"31-60",IF(F2<=90,"61-90","90+"))))
A3: 0009000068 | B3: 0000100508 | C3: 44936 | D3: 44996 | E3: 2248.49 | F3: =Summary!$B$3-D3 | G3: =IF(D3>Summary!$B$3,"Current",IF(F3<=30,"0-30",IF(F3<=60,"31-60",IF(F3<=90,"61-90","90+"))))
A4: 0009000103 | B4: 0000100345 | C4: 44937 | D4: 44967 | E4: 342.36 | F4: =Summary!$B$3-D4 | G4: =IF(D4>Summary!$B$3,"Current",IF(F4<=30,"0-30",IF(F4<=60,"31-60",IF(F4<=90,"61-90","90+"))))
A5: 0009000108 | B5: 0000100001 | C5: 44947 | D5: 44992 | E5: 825.07 | F5: =Summary!$B$3-D5 | G5: =IF(D5>Summary!$B$3,"Current",IF(F5<=30,"0-30",IF(F5<=60,"31-60",IF(F5<=90,"61-90","90+"))))
A6: 0009000156 | B6: 0000100416 | C6: 44943 | D6: 44988 | E6: 1108.45 | F6: =Summary!$B$3-D6 | G6: =IF(D6>Summary!$B$3,"Current",IF(F6<=30,"0-30",IF(F6<=60,"31-60",IF(F6<=90,"61-90","90+"))))
A7: 0009000214 | B7: 0000100434 | C7: 44943 | D7: 44973 | E7: 694.67 | F7: =Summary!$B$3-D7 | G7: =IF(D7>Summary!$B$3,"Current",IF(F7<=30,"0-30",IF(F7<=60,"31-60",IF(F7<=90,"61-90","90+"))))
A8: 0009000218 | B8: 0000100128 | C8: 44943 | D8: 44973 | E8: 1738.5 | F8: =Summary!$B$3-D8 | G8: =IF(D8>Summary!$B$3,"Current",IF(F8<=30,"0-30",IF(F8<=60,"31-60",IF(F8<=90,"61-90","90+"))))
A9: 0009000359 | B9: 0000100106 | C9: 44950 | D9: 44995 | E9: 1493.65 | F9: =Summary!$B$3-D9 | G9: =IF(D9>Summary!$B$3,"Current",IF(F9<=30,"0-30",IF(F9<=60,"31-60",IF(F9<=90,"61-90","90+"))))
A10: 0009000408 | B10: 0000100196 | C10: 44951 | D10: 44981 | E10: 252.84 | F10: =Summary!$B$3-D10 | G10: =IF(D10>Summary!$B$3,"Current",IF(F10<=30,"0-30",IF(F10<=60,"31-60",IF(F10<=90,"61-90","90+"))))
A11: 0009000508 | B11: 0000100095 | C11: 44960 | D11: 45005 | E11: 1639.64 | F11: =Summary!$B$3-D11 | G11: =IF(D11>Summary!$B$3,"Current",IF(F11<=30,"0-30",IF(F11<=60,"31-60",IF(F11<=90,"61-90","90+"))))
A12: 0009000536 | B12: 0000100219 | C12: 44960 | D12: 44990 | E12: 473.16 | F12: =Summary!$B$3-D12 | G12: =IF(D12>Summary!$B$3,"Current",IF(F12<=30,"0-30",IF(F12<=60,"31-60",IF(F12<=90,"61-90","90+"))))
A13: 0009000589 | B13: 0000100051 | C13: 44964 | D13: 45024 | E13: 465.44 | F13: =Summary!$B$3-D13 | G13: =IF(D13>Summary!$B$3,"Current",IF(F13<=30,"0-30",IF(F13<=60,"31-60",IF(F13<=90,"61-90","90+"))))
... A2556: 0009029838 | B2556: 0000100258 | C2556: 46022 | D2556: 46052 | E2556: 918.96 | F2556: =Summary!$B$3-D2556 | G2556: =IF(D2556>Summary!$B$3,"Current",IF(F2556<=30,"0-30",IF(F2556<=60,"31-60",IF(F2556<=90,"61-90","90+"))))

Sheet Aging
A1: Bucket | B1: Invoices | C1: Amount | D1: % of open AR
A2: Current | B2: =COUNTIFS(AR_Open!$G$2:$G$2556,A2) | C2: =SUMIFS(AR_Open!$E$2:$E$2556,AR_Open!$G$2:$G$2556,A2) | D2: =IFERROR(C2/$C$7,0)
A3: 0-30 | B3: =COUNTIFS(AR_Open!$G$2:$G$2556,A3) | C3: =SUMIFS(AR_Open!$E$2:$E$2556,AR_Open!$G$2:$G$2556,A3) | D3: =IFERROR(C3/$C$7,0)
A4: 31-60 | B4: =COUNTIFS(AR_Open!$G$2:$G$2556,A4) | C4: =SUMIFS(AR_Open!$E$2:$E$2556,AR_Open!$G$2:$G$2556,A4) | D4: =IFERROR(C4/$C$7,0)
A5: 61-90 | B5: =COUNTIFS(AR_Open!$G$2:$G$2556,A5) | C5: =SUMIFS(AR_Open!$E$2:$E$2556,AR_Open!$G$2:$G$2556,A5) | D5: =IFERROR(C5/$C$7,0)
A6: 90+ | B6: =COUNTIFS(AR_Open!$G$2:$G$2556,A6) | C6: =SUMIFS(AR_Open!$E$2:$E$2556,AR_Open!$G$2:$G$2556,A6) | D6: =IFERROR(C6/$C$7,0)
A7: Total | B7: =SUM(B2:B6) | C7: =SUM(C2:C6) | D7: =SUM(D2:D6)

Sheet DSO
A1: Month end | B1: Open AR | C1: Credit sales (trailing 90d) | D1: DSO (days)
A2: 44957 | B2: 538321.56 | C2: 542089.24 | D2: =ROUND(B2/C2*90,2)
A3: 44985 | B3: 1022654.6 | C3: 1229300 | D3: =ROUND(B3/C3*90,2)
A4: 45016 | B4: 1214626.9 | C4: 2025660.5 | D4: =ROUND(B4/C4*90,2)
A5: 45046 | B5: 1420486.3 | C5: 2434791.2 | D5: =ROUND(B5/C5*90,2)
A6: 45077 | B6: 1418985.9 | C6: 2489968.1 | D6: =ROUND(B6/C6*90,2)
A7: 45107 | B7: 1522454.4 | C7: 2692598.5 | D7: =ROUND(B7/C7*90,2)
A8: 45138 | B8: 1357174.2 | C8: 2502417.2 | D8: =ROUND(B8/C8*90,2)
A9: 45169 | B9: 1267262.9 | C9: 2424036 | D9: =ROUND(B9/C9*90,2)
A10: 45199 | B10: 1395261.4 | C10: 2313259.9 | D10: =ROUND(B10/C10*90,2)
A11: 45230 | B11: 1558234.6 | C11: 2519317.4 | D11: =ROUND(B11/C11*90,2)
A12: 45260 | B12: 1803697.2 | C12: 2907017.6 | D12: =ROUND(B12/C12*90,2)
A13: 45291 | B13: 1973415.4 | C13: 3106537 | D13: =ROUND(B13/C13*90,2)
... A37: 46022 | B37: 3062052.1 | C37: 3700121.4 | D37: =ROUND(B37/C37*90,2)

Sheet Variance
A1: Cost centre | B1: Period | C1: Actual | D1: Budget | E1: Variance | F1: Variance %
A2: CC001 | B2: 202501 | C2: 12107.65 | D2: 13046.16 | E2: =C2-D2 | F2: =IFERROR(E2/D2,0)
A3: CC001 | B3: 202502 | C3: 13021.6 | D3: 13151.37 | E3: =C3-D3 | F3: =IFERROR(E3/D3,0)
A4: CC001 | B4: 202503 | C4: 13473.24 | D4: 13256.58 | E4: =C4-D4 | F4: =IFERROR(E4/D4,0)
A5: CC001 | B5: 202504 | C5: 13242.21 | D5: 13361.79 | E5: =C5-D5 | F5: =IFERROR(E5/D5,0)
A6: CC001 | B6: 202505 | C6: 13259.26 | D6: 13467 | E6: =C6-D6 | F6: =IFERROR(E6/D6,0)
A7: CC001 | B7: 202506 | C7: 13819.35 | D7: 13572.21 | E7: =C7-D7 | F7: =IFERROR(E7/D7,0)
A8: CC001 | B8: 202507 | C8: 14247.54 | D8: 13677.43 | E8: =C8-D8 | F8: =IFERROR(E8/D8,0)
A9: CC001 | B9: 202508 | C9: 14371.69 | D9: 13782.64 | E9: =C9-D9 | F9: =IFERROR(E9/D9,0)
A10: CC001 | B10: 202509 | C10: 13659.14 | D10: 13887.85 | E10: =C10-D10 | F10: =IFERROR(E10/D10,0)
A11: CC001 | B11: 202510 | C11: 14039.54 | D11: 13993.06 | E11: =C11-D11 | F11: =IFERROR(E11/D11,0)
A12: CC001 | B12: 202511 | C12: 15318.35 | D12: 15508.1 | E12: =C12-D12 | F12: =IFERROR(E12/D12,0)
A13: CC001 | B13: 202512 | C13: 15707.64 | D13: 15623.83 | E13: =C13-D13 | F13: =IFERROR(E13/D13,0)
... A241: CC020 | B241: 202512 | C241: 22282.71 | D241: 21448.98 | E241: =C241-D241 | F241: =IFERROR(E241/D241,0)

Sheet PnL
A1: Period | B1: Revenue | C1: COGS | D1: Opex | E1: Gross profit | F1: EBIT | G1: Gross margin %
A2: 202301 | B2: 568279.76 | C2: 391446.8 | D2: 215598.59 | E2: =B2-C2 | F2: =E2-D2 | G2: =IFERROR(E2/B2,0)
A3: 202302 | B3: 711260.26 | C3: 496958.14 | D3: 217951.83 | E3: =B3-C3 | F3: =E3-D3 | G3: =IFERROR(E3/B3,0)
A4: 202303 | B4: 831709.73 | C4: 563369.6 | D4: 222426.14 | E4: =B4-C4 | F4: =E4-D4 | G4: =IFERROR(E4/B4,0)
A5: 202304 | B5: 982342.69 | C5: 621444.74 | D5: 222351.12 | E5: =B5-C5 | F5: =E5-D5 | G5: =IFERROR(E5/B5,0)
A6: 202305 | B6: 841220.39 | C6: 584711.32 | D6: 225674.27 | E6: =B6-C6 | F6: =E6-D6 | G6: =IFERROR(E6/B6,0)
A7: 202306 | B7: 1018895.8 | C7: 601424.1 | D7: 228302.79 | E7: =B7-C7 | F7: =E7-D7 | G7: =IFERROR(E7/B7,0)
A8: 202307 | B8: 795467.92 | C8: 524761.72 | D8: 234817.79 | E8: =B8-C8 | F8: =E8-D8 | G8: =IFERROR(E8/B8,0)
A9: 202308 | B9: 770745.75 | C9: 529382.83 | D9: 233642.52 | E9: =B9-C9 | F9: =E9-D9 | G9: =IFERROR(E9/B9,0)
A10: 202309 | B10: 888297.11 | C10: 580392.81 | D10: 237923.67 | E10: =B10-C10 | F10: =E10-D10 | G10: =IFERROR(E10/B10,0)
A11: 202310 | B11: 994258.5 | C11: 673812.52 | D11: 241376.42 | E11: =B11-C11 | F11: =E11-D11 | G11: =IFERROR(E11/B11,0)
A12: 202311 | B12: 1155205.3 | C12: 741051.94 | D12: 267081.19 | E12: =B12-C12 | F12: =E12-D12 | G12: =IFERROR(E12/B12,0)
A13: 202312 | B13: 1134576.9 | C13: 758737.96 | D13: 266435.78 | E13: =B13-C13 | F13: =E13-D13 | G13: =IFERROR(E13/B13,0)
... A37: 202512 | B37: 1341273.1 | C37: 894344.05 | D37: 339905.74 | E37: =B37-C37 | F37: =E37-D37 | G37: =IFERROR(E37/B37,0)
